pyDHgripper/__init__.py
pyDHgripper/AG95/Gripper.py
pyDHgripper/AG95/__init__.py
pyDHgripper/DH3/Gripper.py
pyDHgripper/DH3/__init__.py
pyDHgripper/PGE/Gripper.py
pyDHgripper/PGE/__init__.py
pyDHgripper/RGD/Gripper.py
pyDHgripper/RGD/__init__.py
pydhgripper-1.0.2.dist-info/LICENSE
pydhgripper-1.0.2.dist-info/METADATA
pydhgripper-1.0.2.dist-info/WHEEL
pydhgripper-1.0.2.dist-info/top_level.txt
pydhgripper-1.0.2.dist-info/RECORD
