Metadata-Version: 2.1
Name: pydhgripper
Version: 1.0.2
Summary: Python library for controlling the DH gripper
Home-page: https://github.com/han-xudong/pyDHgripper
Author: Yu Jie, Xudong Han
License: MIT
Keywords: DH gripper,robotics,robotic gripper
Classifier: Development Status :: 3 - Alpha
Classifier: Intended Audience :: Developers
Classifier: License :: OSI Approved :: MIT License
Classifier: Programming Language :: Python :: 3
Classifier: Programming Language :: Python :: 3.6
Classifier: Programming Language :: Python :: 3.7
Classifier: Programming Language :: Python :: 3.8
Classifier: Programming Language :: Python :: 3.9
Classifier: Programming Language :: Python :: 3.10
Requires-Python: >=3.6
License-File: LICENSE
Requires-Dist: crcmod ==1.7
Requires-Dist: pyserial ==3.5
